snakemake_interface_software_deployment_plugins/__init__.py
snakemake_interface_software_deployment_plugins/_common.py
snakemake_interface_software_deployment_plugins/registry/__init__.py
snakemake_interface_software_deployment_plugins/registry/plugin.py
snakemake_interface_software_deployment_plugins/settings.py
snakemake_interface_software_deployment_plugins/tests.py
snakemake_interface_software_deployment_plugins-0.9.0.dist-info/METADATA
snakemake_interface_software_deployment_plugins-0.9.0.dist-info/WHEEL
snakemake_interface_software_deployment_plugins-0.9.0.dist-info/licenses/LICENSE
snakemake_interface_software_deployment_plugins-0.9.0.dist-info/RECORD
